strong_typing/VERSION
strong_typing/__init__.py
strong_typing/_display_widget.py
strong_typing/_struct.py
strong_typing/_struct_v3.py
strong_typing/_textualize.py
strong_typing/_versioned_struct.py
strong_typing/typed_containers/__init__.py
strong_typing/typed_containers/_typed_list.py
strong_typing/typed_parameters/__init__.py
strong_typing/typed_parameters/_parameters.py
strong_typing/typed_parameters/normalizers.py
strong_typing-0.3.1.dist-info/DESCRIPTION.rst
strong_typing-0.3.1.dist-info/METADATA
strong_typing-0.3.1.dist-info/RECORD
strong_typing-0.3.1.dist-info/WHEEL
strong_typing-0.3.1.dist-info/metadata.json
strong_typing-0.3.1.dist-info/top_level.txt
