Metadata-Version: 2.0
Name: strong-typing
Version: 0.3.1
Summary: Classes to create strongly typed structures in Python
Home-page: https://github.com/aldebaran/strong_typing.git
Author: Surya Ambrose
Author-email: sambrose@gmail.com
License: BSD-3
Keywords: static-typing strongly-typed structures
Platform: UNKNOWN
Classifier: Development Status :: 3 - Alpha
Classifier: License :: OSI Approved :: BSD License
Classifier: Intended Audience :: Developers
Classifier: Programming Language :: Python :: 2.7
Classifier: Programming Language :: Python :: 3.4
Classifier: Topic :: Software Development :: Libraries :: Python Modules
Classifier: Topic :: Utilities
Requires-Dist: enum34 (>=1.0.4)
Requires-Dist: Qt.py (>=1.0.0)
